wtwco_igloo_cloud_api_client/__init__.py
wtwco_igloo_cloud_api_client/api/__init__.py
wtwco_igloo_cloud_api_client/api/calculation_pools/__init__.py
wtwco_igloo_cloud_api_client/api/calculation_pools/get_calculation_pool.py
wtwco_igloo_cloud_api_client/api/calculation_pools/list_calculation_pools.py
wtwco_igloo_cloud_api_client/api/calculation_pools/list_calculation_pools_for_workspace.py
wtwco_igloo_cloud_api_client/api/data_groups/__init__.py
wtwco_igloo_cloud_api_client/api/data_groups/list_data_groups_for_run.py
wtwco_igloo_cloud_api_client/api/data_table/__init__.py
wtwco_igloo_cloud_api_client/api/data_table/get_data_table_for_run.py
wtwco_igloo_cloud_api_client/api/data_table/get_data_table_for_version.py
wtwco_igloo_cloud_api_client/api/data_tables/__init__.py
wtwco_igloo_cloud_api_client/api/data_tables/list_data_tables_for_run.py
wtwco_igloo_cloud_api_client/api/input_data/__init__.py
wtwco_igloo_cloud_api_client/api/input_data/get_input_data_for_table.py
wtwco_igloo_cloud_api_client/api/input_data/update_input_data.py
wtwco_igloo_cloud_api_client/api/job_status/__init__.py
wtwco_igloo_cloud_api_client/api/job_status/update_job_status.py
wtwco_igloo_cloud_api_client/api/jobs/__init__.py
wtwco_igloo_cloud_api_client/api/jobs/create_job.py
wtwco_igloo_cloud_api_client/api/jobs/get_job.py
wtwco_igloo_cloud_api_client/api/jobs/list_jobs.py
wtwco_igloo_cloud_api_client/api/models/__init__.py
wtwco_igloo_cloud_api_client/api/models/list_models.py
wtwco_igloo_cloud_api_client/api/models/list_models_for_workspace.py
wtwco_igloo_cloud_api_client/api/o_data/__init__.py
wtwco_igloo_cloud_api_client/api/o_data/get_o_data_for_project.py
wtwco_igloo_cloud_api_client/api/o_data/get_o_data_for_run.py
wtwco_igloo_cloud_api_client/api/output_data/__init__.py
wtwco_igloo_cloud_api_client/api/output_data/get_output_data.py
wtwco_igloo_cloud_api_client/api/projects/__init__.py
wtwco_igloo_cloud_api_client/api/projects/create_project.py
wtwco_igloo_cloud_api_client-5.0.0.dist-info/licenses/LICENSE.txt
wtwco_igloo_cloud_api_client-5.0.0.dist-info/METADATA
wtwco_igloo_cloud_api_client-5.0.0.dist-info/WHEEL
wtwco_igloo_cloud_api_client-5.0.0.dist-info/RECORD
