Metadata-Version: 2.4
Name: wtwco-igloo-cloud-api-client
Version: 5.0.0
Summary: A client library for accessing Igloo Cloud API
License: MIT
License-File: LICENSE.txt
Author: WTW
Author-email: software.support@wtwco.com
Requires-Python: >=3.9,<4.0
Classifier: License :: OSI Approved :: MIT License
Classifier: Programming Language :: Python :: 3
Classifier: Programming Language :: Python :: 3.9
Classifier: Programming Language :: Python :: 3.10
Classifier: Programming Language :: Python :: 3.11
Classifier: Programming Language :: Python :: 3.12
Classifier: Programming Language :: Python :: 3.13
Classifier: Programming Language :: Python :: 3.14
Requires-Dist: attrs (>=25.3.0,<26.0.0)
Requires-Dist: h11 (>=0.16.0,<0.17.0)
Requires-Dist: httpx (>=0.20.0,<1.0)
Requires-Dist: python-dateutil (>=2.8.0,<3.0.0)
